volcano/test/__init__.py
volcano/test/tcp_channel.py
volcano/test/volcano_client.py
volcano/test/wait.py
volcano_test-0.3.6.dist-info/LICENSE
volcano_test-0.3.6.dist-info/METADATA
volcano_test-0.3.6.dist-info/WHEEL
volcano_test-0.3.6.dist-info/top_level.txt
volcano_test-0.3.6.dist-info/RECORD
